rosey/Errors.py
rosey/__init__.py
rosey/graphing.py
rosey/helpers.py
rosey/keras.py
rosey/models.py
rosey/stats.py
rosey/transform.py
rosey-0.15052018.dist-info/DESCRIPTION.rst
rosey-0.15052018.dist-info/METADATA
rosey-0.15052018.dist-info/RECORD
rosey-0.15052018.dist-info/WHEEL
rosey-0.15052018.dist-info/metadata.json
rosey-0.15052018.dist-info/top_level.txt
